pytrask/__init__.py
pytrask/__main__.py
pytrask/pytraskgui.py
pytrask/trasker.py
pytrask/templates/ui.html
pytrask-0.0.4.dist-info/LICENSE
pytrask-0.0.4.dist-info/METADATA
pytrask-0.0.4.dist-info/WHEEL
pytrask-0.0.4.dist-info/top_level.txt
pytrask-0.0.4.dist-info/RECORD
