Metadata-Version: 2.1
Name: pytrask
Version: 0.0.4
Summary: Minimalist Kanban task management tool
Home-page: https://github.com/Nimelli/pytrask
Author: Nimelli
Author-email: 
License: UNKNOWN
Platform: UNKNOWN
Classifier: Programming Language :: Python :: 3
Classifier: License :: OSI Approved :: GNU General Public License v3 (GPLv3)
Classifier: Operating System :: OS Independent
Requires-Python: >=3.6
Requires-Dist: flask
Requires-Dist: flaskwebgui
